type_enforced/__init__.py
type_enforced/enforcer.py
type_enforced/utils.py
type_enforced-2.3.0.dist-info/licenses/LICENSE
type_enforced-2.3.0.dist-info/METADATA
type_enforced-2.3.0.dist-info/WHEEL
type_enforced-2.3.0.dist-info/top_level.txt
type_enforced-2.3.0.dist-info/RECORD
