Metadata-Version: 2.4
Name: type_enforced
Version: 2.3.0
Summary: A pure python type enforcer for python type annotations
Author-email: Connor Makowski <conmak@mit.edu>
Project-URL: Homepage, https://github.com/connor-makowski/type_enforced
Project-URL: Bug Tracker, https://github.com/connor-makowski/type_enforced/issues
Project-URL: Documentation, https://connor-makowski.github.io/type_enforced/type_enforced/enforcer.html
Classifier: Programming Language :: Python :: 3
Classifier: License :: OSI Approved :: MIT License
Classifier: Operating System :: OS Independent
Requires-Python: >=3.11
License-File: LICENSE
Dynamic: license-file
